[
  {
    "id": "taim-al-falasi",
    "name": "Taim AlFalasi",
    "handle": "@taimalfalasi",
    "image": "/images/celebrities/taim-al-falasi.webp"
  },
  {
    "id": "mona-kattan",
    "name": "Mona Kattan",
    "handle": "@monakattan",
    "image": "/images/celebrities/mona-kattan.webp"
  },
  {
    "id": "aseel",
    "name": "Aseel",
    "handle": "@aseel",
    "image": "/images/celebrities/aseel.webp"
  },
  {
    "id": "mohamed-ramadan",
    "name": "Mohamed Ramadan",
    "handle": "@mohamedramadanws",
    "image": "/images/celebrities/mohamed-ramadan.webp"
  },
  {
    "id": "saoud-alkaabi",
    "name": "Saoud Alkaabi",
    "handle": "@saoudalkaabi",
    "image": "/images/celebrities/saoud-alkaabi.webp"
  },
  {
    "id": "rita-kahawaty",
    "name": "Rita Kahawaty",
    "handle": "@ritakahawaty",
    "image": "/images/celebrities/rita-kahawaty.webp"
  },
  {
    "id": "zoya-sakr",
    "name": "Zoya Sakr",
    "handle": "@zoyasakr",
    "image": "/images/celebrities/zoya-sakr.webp"
  },
  {
    "id": "asallah-kamel",
    "name": "Asallah Kamel",
    "handle": "@asallahkamel",
    "image": "/images/celebrities/asallah-kamel.webp"
  },
  {
    "id": "ahmed-twistedcurlz",
    "name": "Ahmed",
    "handle": "@twistedcurlz",
    "image": "/images/celebrities/ahmed-twistedcurlz.webp"
  },
  {
    "id": "aliyah-raey",
    "name": "Aliyah Raey",
    "handle": "@aliyahraey",
    "image": "/images/celebrities/aliyah-raey.webp"
  },
  {
    "id": "lamiya-slimani",
    "name": "Lamiya Slimani",
    "handle": "@lamiyaslimani",
    "image": "/images/celebrities/lamiya-slimani.webp"
  },
  {
    "id": "leen-jadan",
    "name": "Leen Jadan",
    "handle": "@leenjadan",
    "image": "/images/celebrities/leen-jadan.webp"
  },
  {
    "id": "dalia-el-ali",
    "name": "Dalia El Ali",
    "handle": "@deebydalia",
    "image": "/images/celebrities/dalia-el-ali.webp"
  },
  {
    "id": "diana-ganeeva",
    "name": "Diana Ganeeva",
    "handle": "@diana.dxb",
    "image": "/images/celebrities/diana-ganeeva.webp"
  },
  {
    "id": "heba-saad",
    "name": "Heba Saad",
    "handle": "@habah_saad",
    "image": "/images/celebrities/heba-saad.webp"
  }
]
